sqlmate/__init__.py
sqlmate/cli.py
sqlmate/version.py
sqlmate-0.0.1.dist-info/licenses/LICENSE
sqlmate-0.0.1.dist-info/METADATA
sqlmate-0.0.1.dist-info/WHEEL
sqlmate-0.0.1.dist-info/entry_points.txt
sqlmate-0.0.1.dist-info/top_level.txt
sqlmate-0.0.1.dist-info/RECORD
