Metadata-Version: 2.4
Name: sqlmate
Version: 0.0.1
Summary: A simple SQL utility package
Home-page: https://github.com/JiehangXie/sqlmate
Author: Jiehang Xie
Author-email: Your Name <your.email@example.com>
License: MIT
Project-URL: Homepage, https://github.com/yourusername/sqlmate
Project-URL: Repository, https://github.com/yourusername/sqlmate
Project-URL: Issues, https://github.com/yourusername/sqlmate/issues
Classifier: Development Status :: 3 - Alpha
Classifier: Intended Audience :: Developers
Classifier: License :: OSI Approved :: MIT License
Classifier: Operating System :: OS Independent
Classifier: Programming Language :: Python :: 3
Classifier: Programming Language :: Python :: 3.7
Classifier: Programming Language :: Python :: 3.8
Classifier: Programming Language :: Python :: 3.9
Classifier: Programming Language :: Python :: 3.10
Classifier: Programming Language :: Python :: 3.11
Requires-Python: >=3.8
License-File: LICENSE
Dynamic: author
Dynamic: home-page
Dynamic: license-file
Dynamic: requires-python
